{
    "Ar36": {
        "error": 0.5590258694254938,
        "error_type": "",
        "fit": "previous",
        "references": [
            {
                "exclude": false,
                "record_id": "ba-01-N-2185"
            }
        ],
        "value": 24.6540619641949
    },
    "Ar37": {
        "error": 2.367157202877379e-07,
        "error_type": "",
        "fit": "previous",
        "references": [
            {
                "exclude": false,
                "record_id": "ba-01-N-2185"
            }
        ],
        "value": 3.1801598531919733e-06
    },
    "Ar38": {
        "error": 2.7393102838144365e-07,
        "error_type": "",
        "fit": "previous",
        "references": [
            {
                "exclude": false,
                "record_id": "ba-01-N-2185"
            }
        ],
        "value": -3.5459621393560135e-07
    },
    "Ar39": {
        "error": 3.63052639967582e-07,
        "error_type": "",
        "fit": "previous",
        "references": [
            {
                "exclude": false,
                "record_id": "ba-01-N-2185"
            }
        ],
        "value": -2.2419603274203457e-06
    },
    "Ar40": {
        "error": 3.068435000631392e-06,
        "error_type": "",
        "fit": "previous",
        "references": [
            {
                "exclude": false,
                "record_id": "ba-01-N-2185"
            }
        ],
        "value": 8.964297257488808e-05
    }
}