{
    "Ar36": {
        "error": 0.6218406133207764,
        "error_type": "",
        "fit": "previous",
        "references": [
            {
                "exclude": false,
                "record_id": "ba-01-N-2462"
            }
        ],
        "value": 16.99811934908651
    },
    "Ar37": {
        "error": 1.7987622235029048e-07,
        "error_type": "",
        "fit": "previous",
        "references": [
            {
                "exclude": false,
                "record_id": "ba-01-N-2462"
            }
        ],
        "value": 3.963820780296421e-06
    },
    "Ar38": {
        "error": 2.8261044081777396e-07,
        "error_type": "",
        "fit": "previous",
        "references": [
            {
                "exclude": false,
                "record_id": "ba-01-N-2462"
            }
        ],
        "value": 1.8683186198776414e-06
    },
    "Ar39": {
        "error": 2.3159310452742267e-07,
        "error_type": "",
        "fit": "previous",
        "references": [
            {
                "exclude": false,
                "record_id": "ba-01-N-2462"
            }
        ],
        "value": 4.464320447557595e-07
    },
    "Ar40": {
        "error": 2.4649189657373494e-06,
        "error_type": "",
        "fit": "previous",
        "references": [
            {
                "exclude": false,
                "record_id": "ba-01-N-2462"
            }
        ],
        "value": 3.728260102819683e-05
    }
}